Metadata-Version: 2.1
Name: cbrf_exchange_rates
Version: 0.0.1
Summary: Client for The Central Bank of the Russian Federation APIs
Home-page: https://github.com/cooper30/cbrf_exchange_rates.git
Author: Nikita Zvekov
Author-email: cooper30@mail.ru
License: MIT
Classifier: Development Status :: 4 - Beta
Classifier: License :: OSI Approved :: MIT License
Classifier: Environment :: Console
Classifier: Programming Language :: Python :: 3
Classifier: Operating System :: OS Independent
Requires-Python: ~=3.12
License-File: LICENSE
Requires-Dist: requests
